requests_gpgauthlib/__init__.py
requests_gpgauthlib/exceptions.py
requests_gpgauthlib/gpgauth_api.py
requests_gpgauthlib/gpgauth_protocol.py
requests_gpgauthlib/gpgauth_session.py
requests_gpgauthlib/utils.py
requests_gpgauthlib-0.1.2.dist-info/METADATA
requests_gpgauthlib-0.1.2.dist-info/RECORD
requests_gpgauthlib-0.1.2.dist-info/WHEEL
requests_gpgauthlib-0.1.2.dist-info/top_level.txt
tests/__init__.py
tests/unit/__init__.py
tests/unit/test_gpgauthsession.py
tests/unit/test_utils.py
