Metadata-Version: 2.1
Name: requests-gpgauthlib
Version: 0.1.2
Summary: requests_gpgauthlib - A requests GPGAuth authentication library
Home-page: https://github.com/liip/requests_gpgauthlib
Author: Didier 'OdyX' Raboud
Author-email: odyx@liip.ch
License: UNKNOWN
Platform: UNKNOWN
Requires-Dist: python-gnupg
Requires-Dist: requests
